genclf/__init__.py
genclf/genclf.py
genclf/models/gender_logit_model.pkl
genclf/models/gender_nv_model.pkl
genclf/models/gender_vectorizer.pkl
genclf-0.0.1.dist-info/WHEEL
genclf-0.0.1.dist-info/METADATA
genclf-0.0.1.dist-info/RECORD
