Metadata-Version: 2.1
Name: genclf
Version: 0.0.1
Summary: Gender Classifier ML Package for classifying gender using firstname
Home-page: https://github.com/Jcharis/genclf
License: MIT
Keywords: gender classifier,jcharistech,genclf,machine learning
Author: JCharis
Author-email: jcharistech@gmail.com
Requires-Python: >=3.7,<4.0
Classifier: License :: OSI Approved :: MIT License
Classifier: Operating System :: OS Independent
Classifier: Programming Language :: Python :: 3
Classifier: Programming Language :: Python :: 3.7
Classifier: Programming Language :: Python :: 3.8
Requires-Dist: joblib (>=0.14.0,<0.15.0)
Requires-Dist: scikit-learn (>=0.22.0,<0.23.0)
Project-URL: Repository, https://github.com/Jcharis/genclf
